{"argument_graph_id":"nf-4db338dcf09d3c6644542c152ab42289","classification":"true_conflict","confidence":0.95,"conflict_id":"nf-caf5b8a475bd89485b49a8a9f0a9056e","conflict_type":"norm_contradiction","human_review_question_en":"In sepsis treatment, the beta-lactam recommendation conflicts with the contraindication. Please verify the priority for patients with allergy history.","human_review_question_ja":"敗血症治療において、βラクタム系抗菌薬の推奨と禁忌が矛盾しています。アレルギー既往患者への優先順位を確認してください。","minimal_artifact_set":["sha256:3229752b8cb70aae5cf352dd2e666a902ae7fe5543c4366150b9c906323ed21a","sha256:464892d106a2ec5b968a58260249fa08cddb03f610435c73ac81ac6aeee6a522","sha256:67856fd669a1a58517b7eb8d8e1104c1e8edab33de476ba9854f3bc2b8dde28d","sha256:f688daf59b8abd382f81678cc8919d75c43aa422777bfe6d49c6698b9898fa47"],"normalized_view":{"rule_contraindicate":{"action":"administer beta_lactam","direction":"against","rule_id":"rule_bl_anaphylaxis_contra","strength":"strong"},"rule_recommend":{"action":"administer beta_lactam","direction":"for","rule_id":"rule_sepsis_bl_recommend","strength":"strong"},"shared_context":"(dx sepsis) AND (allergy_history beta_lactam anaphylaxis)"},"repair_candidates":[{"exception":"beta_lactam_anaphylaxis","rationale":"Exclude allergy patients from recommendation scope","rule":"rule_sepsis_bl_recommend","type":"add_exception"},{"rationale":"Absolute contraindication overrides recommendation","superior":"rule_bl_anaphylaxis_contra","type":"add_priority"}],"severity":"high","solver_evidence":[{"description":"Shared context satisfiable: patient with sepsis AND beta-lactam anaphylaxis history exists","encoding":"smt2","solver":"z3","status":"sat"}],"source_spans":["span_contra_bl_allergy","span_rec_sepsis_bl"],"witness":"nf-7260b8bcfb273c6ea1a5764faa86f46d"}